demo/__init__.py
demo/local_settings.py
demo/sass_variables.py
demo/settings.py
demo/urls.py
demo/views.py
demo/wsgi.py
psu_scheduler/__init__.py
psu_scheduler/admin.py
psu_scheduler/apps.py
psu_scheduler/decorators.py
psu_scheduler/urls.py
psu_scheduler/views.py
psu_scheduler/classes/__init__.py
psu_scheduler/migrations/0001_initial.py
psu_scheduler/migrations/0002_auto_20210127_1653.py
psu_scheduler/migrations/0003_jobexecution_http_status.py
psu_scheduler/migrations/0004_auto_20220720_1621.py
psu_scheduler/migrations/__init__.py
psu_scheduler/models/__init__.py
psu_scheduler/models/endpoint_definition.py
psu_scheduler/models/job_execution.py
psu_scheduler/models/scheduled_job.py
psu_scheduler/services/__init__.py
psu_scheduler/services/scheduler_service.py
psu_scheduler/templates/psu_scheduler/_endpoint_tr.html
psu_scheduler/templates/psu_scheduler/_schedule_job_tr.html
psu_scheduler/templates/psu_scheduler/endpoints.html
psu_scheduler/templates/psu_scheduler/executions.html
psu_scheduler/templates/psu_scheduler/scheduled_jobs.html
psu_scheduler/templatetags/__init__.py
psu_scheduler/templatetags/scheduler_taglib.py
psu_scheduler/tests/__init__.py
psu_scheduler/tests/test_applications.py
psu_scheduler-2.0.1.dist-info/METADATA
psu_scheduler-2.0.1.dist-info/WHEEL
psu_scheduler-2.0.1.dist-info/top_level.txt
psu_scheduler-2.0.1.dist-info/RECORD
