Metadata-Version: 2.1
Name: psu-scheduler
Version: 2.0.1
Summary: scheduler extension for PSU Django apps
Home-page: https://github.com/PSU-OIT-ARC/django-psu-scheduler
Author: Mike Gostomski
Author-email: mjg@pdx.edu
License: MIT License
Platform: UNKNOWN
Classifier: Framework :: Django :: 2.2
Classifier: License :: OSI Approved :: MIT License
Classifier: Operating System :: OS Independent
Classifier: Programming Language :: Python :: 3.6
Requires-Dist: psu-base (>=6.0.0)
Requires-Dist: requests-futures
